tcod/clock/__init__.py
tcod/clock/py.typed
tcod/clock/test_clock.py
tcod_clock-1.0.1.dist-info/LICENSE
tcod_clock-1.0.1.dist-info/WHEEL
tcod_clock-1.0.1.dist-info/METADATA
tcod_clock-1.0.1.dist-info/RECORD
