Metadata-Version: 2.1
Name: tcod-clock
Version: 1.0.1
Summary: Track and limit framerate of a program.
Author-email: Kyle Benesch <4b796c65+github@gmail.com>
Requires-Python: >=3.8
Classifier: Development Status :: 5 - Production/Stable
Classifier: Intended Audience :: Developers
Classifier: License :: OSI Approved :: MIT License
Classifier: Operating System :: OS Independent
Classifier: Programming Language :: Python :: 3
Classifier: Topic :: Software Development :: Libraries :: Python Modules
Classifier: Typing :: Typed
Project-URL: Changelog, https://github.com/HexDecimal/python-tcod-clock/blob/main/CHANGELOG.md
Project-URL: Documentation, https://python-tcod-clock.readthedocs.io
Project-URL: Home, https://github.com/HexDecimal/python-tcod-clock
Project-URL: Source, https://github.com/HexDecimal/python-tcod-clock
